bids/__init__.py
bids/__main__.py
bids/_version.py
bids/cli.py
bids/config.py
bids/conftest.py
bids/due.py
bids/exceptions.py
bids/utils.py
bids/ext/__init__.py
bids/external/__init__.py
bids/external/inflect.py
bids/layout/__init__.py
bids/layout/db.py
bids/layout/index.py
bids/layout/layout.py
bids/layout/models.py
bids/layout/utils.py
bids/layout/validation.py
bids/layout/writing.py
bids/layout/config/bids.json
bids/layout/config/derivatives.json
bids/layout/tests/__init__.py
bids/layout/tests/conftest.py
bids/layout/tests/test_db.py
bids/layout/tests/test_layout.py
bids/layout/tests/test_layout_on_examples.py
bids/layout/tests/test_models.py
bids/layout/tests/test_path_building.py
bids/layout/tests/test_remote_bids.py
bids/layout/tests/test_rootpath.py
bids/layout/tests/test_utils.py
bids/layout/tests/test_validation.py
bids/layout/tests/test_writing.py
bids/layout/tests/data/sample_validation_config.json
bids/modeling/__init__.py
bids/modeling/auto_model.py
bids/modeling/hrf.py
bids/modeling/model_spec.py
bids/modeling/statsmodels.py
bids/modeling/report/__init__.py
bids/modeling/report/base.py
bids/modeling/report/report_template.jinja
bids/modeling/report/utils.py
bids/modeling/report/viz.py
bids/modeling/tests/__init__.py
bids/modeling/tests/test_automodel.py
bids/modeling/tests/test_hrf.py
bids/modeling/tests/test_model_spec.py
bids/modeling/tests/test_statsmodels.py
bids/modeling/tests/test_transformations.py
bids/modeling/transformations/__init__.py
bids/modeling/transformations/base.py
bids/modeling/transformations/compute.py
bids/modeling/transformations/munge.py
bids/reports/__init__.py
bids/reports/conftest.py
bids/reports/parameters.py
bids/reports/parsing.py
bids/reports/report.py
bids/reports/utils.py
bids/reports/config/converters.json
bids/reports/tests/__init__.py
bids/reports/tests/test_parameters.py
bids/reports/tests/test_parsing.py
bids/reports/tests/test_report.py
bids/tests/__init__.py
bids/tests/test_cli.py
bids/tests/test_config.py
pybids-0.21.0.dist-info/licenses/LICENSE
pybids-0.21.0.dist-info/METADATA
pybids-0.21.0.dist-info/WHEEL
pybids-0.21.0.dist-info/entry_points.txt
pybids-0.21.0.dist-info/top_level.txt
pybids-0.21.0.dist-info/RECORD
