Metadata-Version: 2.4
Name: pybids
Version: 0.21.0
Summary: bids: interface with datasets conforming to BIDS
Author-email: PyBIDS Developers <bids-discussion@googlegroups.com>
License: The MIT License (MIT)
Project-URL: Homepage, https://github.com/bids-standard/pybids
Project-URL: Bug Tracker, https://github.com/bids-standard/pybids/issues
Keywords: BIDS,neuroimaging
Classifier: Development Status :: 3 - Alpha
Classifier: Environment :: Console
Classifier: Intended Audience :: Science/Research
Classifier: License :: OSI Approved :: MIT License
Classifier: Operating System :: OS Independent
Classifier: Programming Language :: Python
Classifier: Programming Language :: Python :: 3
Classifier: Topic :: Scientific/Engineering
Requires-Python: >=3.10
License-File: LICENSE
Requires-Dist: numpy>=1.24
Requires-Dist: scipy>=1.10
Requires-Dist: nibabel>=5.0
Requires-Dist: pandas>=2.0
Requires-Dist: formulaic>=0.3
Requires-Dist: sqlalchemy>=1.4.31
Requires-Dist: bids-validator>=1.14.7
Requires-Dist: num2words>=0.5.10
Requires-Dist: click>=8.0
Requires-Dist: universal_pathlib>=0.2.2
Requires-Dist: frozendict>=2.3
Provides-Extra: doc
Requires-Dist: sphinx>=6.2; extra == "doc"
Requires-Dist: numpydoc; extra == "doc"
Requires-Dist: sphinx_rtd_theme; extra == "doc"
Requires-Dist: myst_nb; extra == "doc"
Requires-Dist: jupytext; extra == "doc"
Provides-Extra: plotting
Requires-Dist: graphviz; extra == "plotting"
Provides-Extra: test
Requires-Dist: pytest>=8; extra == "test"
Requires-Dist: pytest-cov>=7; extra == "test"
Requires-Dist: bsmschema>=0.1; extra == "test"
Requires-Dist: coverage[toml]>=7; extra == "test"
Requires-Dist: altair>=5; extra == "test"
Requires-Dist: pytest-xdist>=3.8; extra == "test"
Requires-Dist: s3fs>=2025; extra == "test"
Provides-Extra: model-reports
Requires-Dist: jinja2; extra == "model-reports"
Requires-Dist: altair; extra == "model-reports"
Provides-Extra: tutorial
Requires-Dist: nbconvert; extra == "tutorial"
Requires-Dist: jinja2; extra == "tutorial"
Requires-Dist: markupsafe; extra == "tutorial"
Requires-Dist: jupyter_client; extra == "tutorial"
Requires-Dist: ipykernel; extra == "tutorial"
Provides-Extra: docs
Requires-Dist: pybids[doc]; extra == "docs"
Provides-Extra: tests
Requires-Dist: pybids[test]; extra == "tests"
Provides-Extra: ci-tests
Requires-Dist: pybids[test]; extra == "ci-tests"
Provides-Extra: dev
Requires-Dist: pybids[doc,plotting,test]; extra == "dev"
Dynamic: license-file
